my_first_pypi_demo/__init__.py
my_first_pypi_demo-0.0.4.dist-info/METADATA
my_first_pypi_demo-0.0.4.dist-info/WHEEL
my_first_pypi_demo-0.0.4.dist-info/top_level.txt
my_first_pypi_demo-0.0.4.dist-info/RECORD
